MANIFEST.in
README.md
setup.py
paginate/__init__.py
paginate/ext_reverse.py
paginate.egg-info/PKG-INFO
paginate.egg-info/SOURCES.txt
paginate.egg-info/dependency_links.txt
paginate.egg-info/entry_points.txt
paginate.egg-info/not-zip-safe
paginate.egg-info/top_level.txt