Metadata-Version: 1.1
Name: paginate
Version: 0.5.5
Summary: Divides large result sets into pages for easier browsing
Home-page: https://github.com/Signum/paginate
Author: Christoph Haas
Author-email: email@christoph-haas.de
License: MIT
Keywords: pagination paginate pages
Platform: UNKNOWN
Classifier: Programming Language :: Python
Classifier: Development Status :: 4 - Beta
Classifier: Intended Audience :: Developers
Classifier: License :: OSI Approved :: MIT License
Classifier: Topic :: Software Development :: Libraries :: Python Modules
